[
   {
    "name":"alphonso mango",
    "desc":"great Quality of Mango",
    "type":"fruits",
    "banner":"https://rtechchem.com/wp-content/uploads/2020/02/alphonso-mangoes-500x500-1.jpg",
    "unit":1,
    "price":300, 
    "available":true,
    "suplier":"Golden seed firming"
},
{
    "name":"Apples",
    "desc":"great Quality of Apple",
    "type":"fruits",
    "banner":"https://domf5oio6qrcr.cloudfront.net/medialibrary/11525/0a5ae820-7051-4495-bcca-61bf02897472.jpg",
    "unit":1,
    "price":140, 
    "available":true,
    "suplier":"Golden seed firming"
},
{
    "name":"Kesar Mango",
    "desc":"great Quality of Mango",
    "type":"fruits",
    "banner":"https://plantogram.com/wa-data/public/shop/products/55/06/655/images/1256/1256.970.jpg",
    "unit":1,
    "price":170, 
    "available":true,
    "suplier":"Golden seed firming"
}, 
{
    "name":"Langra Mango",
    "desc":"great Quality of Mango",
    "type":"fruits",
    "banner":"https://www.friendscargo.no/wp-content/uploads/2021/02/fcs-443-mango-deshri.jpg",
    "unit":1,
    "price":280, 
    "available":true,
    "suplier":"Golden seed firming"
},
{
    "name":"Broccoli",
    "desc":"great Quality of Fresh Vegetable",
    "type":"vegetables",
    "banner":"https://chefsmandala.com/wp-content/uploads/2018/03/Broccoli.jpg",
    "unit":1,
    "price":280, 
    "available":true,
    "suplier":"Golden seed firming"
},
{
    "name":"Cauliflower",
    "desc":"great Quality of Fresh Vegetable",
    "type":"vegetables",
    "banner":"https://domf5oio6qrcr.cloudfront.net/medialibrary/5299/h1018g16207257715328.jpg",
    "unit":1,
    "price":280, 
    "available":true,
    "suplier":"Golden seed firming"
},
{
    "name":"Olive Oil",
    
    "desc":"great Quality of Oil",
    "type":"oils",
    "banner":"https://www.lottemart.vn/media/catalog/product/cache/0x0/8/4/8410660306268.jpg",
    "unit":1,
    "price":400, 
    "available":true,
    "suplier":"Golden seed firming"
}
]
